gen_py_tool/__init__.py
gen_py_tool/py.typed
gen_py_tool/conf/gen_py_tool.cfg
gen_py_tool/conf/gen_py_tool.logo
gen_py_tool/conf/gen_py_tool_util.cfg
gen_py_tool/conf/project.yaml
gen_py_tool/conf/template/gen/editorconfig.template
gen_py_tool/conf/template/gen/gen_class.template
gen_py_tool/conf/template/gen/gen_config.template
gen_py_tool/conf/template/gen/gen_config_util.template
gen_py_tool/conf/template/gen/gen_log.template
gen_py_tool/conf/template/gen/gen_logo.template
gen_py_tool/conf/template/gen/gen_pro_class.template
gen_py_tool/conf/template/gen/gen_pro_yaml.template
gen_py_tool/conf/template/gen/gen_read_template.template
gen_py_tool/conf/template/gen/gen_run.template
gen_py_tool/conf/template/gen/gen_write_template.template
gen_py_tool/conf/template/gen/test.template
gen_py_tool/conf/template/tool/editorconfig.template
gen_py_tool/conf/template/tool/tool_class.template
gen_py_tool/conf/template/tool/tool_config.template
gen_py_tool/conf/template/tool/tool_config_util.template
gen_py_tool/conf/template/tool/tool_log.template
gen_py_tool/conf/template/tool/tool_logo.template
gen_py_tool/conf/template/tool/tool_run.template
gen_py_tool/log/gen_py_tool.log
gen_py_tool/pro/__init__.py
gen_py_tool/pro/read_template.py
gen_py_tool/pro/write_template.py
usr/local/bin/gen_py_tool_run.py
gen_py_tool-1.3.8.dist-info/LICENSE
gen_py_tool-1.3.8.dist-info/METADATA
gen_py_tool-1.3.8.dist-info/WHEEL
gen_py_tool-1.3.8.dist-info/top_level.txt
gen_py_tool-1.3.8.dist-info/RECORD
